<T3DataStructure>
	<sheets>
		<sDEF>
			<ROOT>
				<sheetTitle>Settings</sheetTitle>
				<type>array</type>
				<el>
					<containerWrapper>
						<label>Wrapp into a container </label>
						<config>
							<type>select</type>
							<renderType>selectSingle</renderType>
							<items type="array">
								<numIndex index="0">
									<label>no container</label>
									<value></value>
								</numIndex>
								<numIndex index="1">
									<label>container</label>
									<value>container</value>
								</numIndex>
								<numIndex index="2">
									<label>container-sm</label>
									<value>container-sm</value>
								</numIndex>
								<numIndex index="3">
									<label>container-md</label>
									<value>container-md</value>
								</numIndex>
								<numIndex index="4">
									<label>container-lg</label>
									<value>container-lg</value>
								</numIndex>
								<numIndex index="5">
									<label>container-xl</label>
									<value>container-xl</value>
								</numIndex>
								<numIndex index="6">
									<label>container-xxl</label>
									<value>container-xxl</value>
								</numIndex>
								<numIndex index="7">
									<label>container-fluid</label>
									<value>container-fluid</value>
								</numIndex>
							</items>
							<default></default>
						</config>
					</containerWrapper>
				</el>
			</ROOT>
		</sDEF>
	</sheets>
</T3DataStructure>
